odoo/addons/bank_accounts_report/README.rst
odoo/addons/bank_accounts_report/__init__.py
odoo/addons/bank_accounts_report/__manifest__.py
odoo/addons/bank_accounts_report/i18n/es.po
odoo/addons/bank_accounts_report/models/__init__.py
odoo/addons/bank_accounts_report/models/account_move.py
odoo/addons/bank_accounts_report/models/account_payment_mode.py
odoo/addons/bank_accounts_report/models/sale_order.py
odoo/addons/bank_accounts_report/readme/CONFIGURE.md
odoo/addons/bank_accounts_report/readme/CONTRIBUTORS.md
odoo/addons/bank_accounts_report/readme/INSTALL.md
odoo/addons/bank_accounts_report/readme/USAGE.md
odoo/addons/bank_accounts_report/reports/account_invoice.xml
odoo/addons/bank_accounts_report/reports/sale_order.xml
odoo/addons/bank_accounts_report/static/description/icon.png
odoo/addons/bank_accounts_report/tests/__init__.py
odoo/addons/bank_accounts_report/tests/test_sale_order.py
odoo/addons/bank_accounts_report/views/account_payment_mode.xml
odoo_addon_bank_accounts_report-18.0.1.0.0.dist-info/METADATA
odoo_addon_bank_accounts_report-18.0.1.0.0.dist-info/WHEEL
odoo_addon_bank_accounts_report-18.0.1.0.0.dist-info/top_level.txt
odoo_addon_bank_accounts_report-18.0.1.0.0.dist-info/RECORD
