Metadata-Version: 2.1
Name: odoo-addon-bank_accounts_report
Version: 18.0.1.0.0
Requires-Python: >=3.10
Requires-Dist: odoo-addon-account_banking_mandate==18.0.*
Requires-Dist: odoo-addon-account_payment_mode==18.0.*
Requires-Dist: odoo-addon-account_payment_sale==18.0.*
Requires-Dist: odoo==18.0.*
Summary: Choose which bank accounts will be displayed on invoice and sale order reports
Home-page: https://github.com/sygel-technology/sy-account-invoicing
License: AGPL-3
Author: QubiQ, Odoo Community Association (OCA)
Author-email: support@odoo-community.org
Classifier: Programming Language :: Python
Classifier: Framework :: Odoo
Classifier: Framework :: Odoo :: 18.0
Classifier: License :: OSI Approved :: GNU Affero General Public License v3
